{
    "MATCH": "Milan vs Inter",
    "CASA": {
        "Squadra": "AC Milan",
        "Modulo": "3-5-2",
        "Rating": "19.06/25",
        "1_TITOLARI": [
            "GK - Mike Maignan (7.9)",
            "DIF - Alexis Saelemaekers (7.5)",
            "DIF - Strahinja Pavlovi\u0107 (6.9)",
            "DIF - Matteo Gabbia (5.9)",
            "MID - Luka Modri\u0107 (7.3)",
            "MID - Youssouf Fofana (6.5)",
            "MID - Adrien Rabiot (8.0)",
            "MID - Samuele Ricci (7.7)",
            "MID - Ardon Jashari (7.8)",
            "ATT - Rafael Le\u00e3o (7.7)",
            "ATT - Ruben Loftus-Cheek (5.4)"
        ],
        "2_PANCHINA": [
            "GK - Pietro Terracciano (8.0)",
            "DIF - Fikayo Tomori (8.1)",
            "DIF - Davide Bartesaghi (6.9)",
            "MID (da DIF) - Koni De Winter (6.5)",
            "MID (da DIF) - Pervis Estupi\u00f1\u00e1n (6.4)",
            "ATT - Santiago Gim\u00e9nez (4.9)",
            "ATT - Christopher Nkunku (6.2)"
        ]
    },
    "OSPITE": {
        "Squadra": "Inter",
        "Modulo": "3-5-2",
        "Rating": "19.14/25",
        "1_TITOLARI": [
            "GK - Yann Sommer (6.1)",
            "DIF - Alessandro Bastoni (7.6)",
            "DIF - Manuel Akanji (6.8)",
            "DIF - Federico Dimarco (6.4)",
            "MID - Nicol\u00f2 Barella (7.5)",
            "MID - Hakan \u00c7alhano\u011flu (8.2)",
            "MID - Petar Sucic (7.4)",
            "MID - Piotr Zieli\u0144ski (7.9)",
            "MID - Henrikh Mkhitaryan (6.6)",
            "ATT - Lautaro Mart\u00ednez (8.0)",
            "ATT - Marcus Thuram (7.7)"
        ],
        "2_PANCHINA": [
            "GK - Josep Martinez (7.8)",
            "DIF - Francesco Acerbi (6.7)",
            "DIF - Denzel Dumfries (6.4)",
            "MID - Davide Frattesi (5.3)",
            "MID - Andy Diouf (6.7)",
            "ATT - Francesco Esposito (6.3)",
            "ATT - Ange-Yoan Bonny (8.7)"
        ]
    }
}