{
  "report_version": "2.2",
  "generated_at": "2026-03-10T06:12:41Z",
  "period": {
    "from": "2026-03-03",
    "to": "2026-03-10",
    "days": 7
  },
  "overview": {
    "total_predictions": 179,
    "correct": 108,
    "errors": 71,
    "error_rate": 39.7,
    "analyzed": 59,
    "not_analyzed": 12,
    "by_type": [
      {
        "type": "SEGNO",
        "total": 47,
        "errors": 24,
        "error_rate": 51.1
      },
      {
        "type": "DOPPIA_CHANCE",
        "total": 36,
        "errors": 14,
        "error_rate": 38.9
      },
      {
        "type": "GOL",
        "total": 96,
        "errors": 33,
        "error_rate": 34.4
      }
    ],
    "standard": {
      "total": 169,
      "correct": 106,
      "errors": 63,
      "error_rate": 37.3,
      "by_type": [
        {
          "type": "SEGNO",
          "total": 37,
          "errors": 16,
          "error_rate": 43.2
        },
        {
          "type": "DOPPIA_CHANCE",
          "total": 36,
          "errors": 14,
          "error_rate": 38.9
        },
        {
          "type": "GOL",
          "total": 96,
          "errors": 33,
          "error_rate": 34.4
        }
      ]
    },
    "alto_rendimento": {
      "total": 10,
      "correct": 2,
      "errors": 8,
      "error_rate": 80.0,
      "profit_loss": -6.5,
      "by_type": [
        {
          "type": "SEGNO",
          "total": 10,
          "errors": 8,
          "error_rate": 80.0
        }
      ]
    }
  },
  "by_source": [
    {
      "source": "A+S_mg",
      "total": 1,
      "correct": 0,
      "errors": 1,
      "error_rate": 100.0,
      "delta": 62.7,
      "flag": "⚠️"
    },
    {
      "source": "C_dg35",
      "total": 2,
      "correct": 0,
      "errors": 2,
      "error_rate": 100.0,
      "delta": 62.7,
      "flag": "⚠️"
    },
    {
      "source": "MC_hw",
      "total": 1,
      "correct": 0,
      "errors": 1,
      "error_rate": 100.0,
      "delta": 62.7,
      "flag": "⚠️"
    },
    {
      "source": "C_mg",
      "total": 8,
      "correct": 4,
      "errors": 4,
      "error_rate": 50.0,
      "delta": 12.7,
      "flag": "⚠️"
    },
    {
      "source": "C",
      "total": 60,
      "correct": 36,
      "errors": 24,
      "error_rate": 40.0,
      "delta": 2.7,
      "flag": ""
    },
    {
      "source": "C_screm",
      "total": 44,
      "correct": 28,
      "errors": 16,
      "error_rate": 36.4,
      "delta": -0.9,
      "flag": ""
    },
    {
      "source": "A",
      "total": 12,
      "correct": 8,
      "errors": 4,
      "error_rate": 33.3,
      "delta": -4.0,
      "flag": "✓"
    },
    {
      "source": "C_combo96",
      "total": 6,
      "correct": 4,
      "errors": 2,
      "error_rate": 33.3,
      "delta": -4.0,
      "flag": "✓"
    },
    {
      "source": "A+S",
      "total": 29,
      "correct": 20,
      "errors": 9,
      "error_rate": 31.0,
      "delta": -6.3,
      "flag": "✓"
    },
    {
      "source": "A_mg",
      "total": 2,
      "correct": 2,
      "errors": 0,
      "error_rate": 0.0,
      "delta": -37.3,
      "flag": "✓"
    },
    {
      "source": "C_hw_mc_conv",
      "total": 1,
      "correct": 1,
      "errors": 0,
      "error_rate": 0.0,
      "delta": -37.3,
      "flag": "✓"
    },
    {
      "source": "C_mc_conv",
      "total": 2,
      "correct": 2,
      "errors": 0,
      "error_rate": 0.0,
      "delta": -37.3,
      "flag": "✓"
    },
    {
      "source": "MC_hw_mc_conv",
      "total": 1,
      "correct": 1,
      "errors": 0,
      "error_rate": 0.0,
      "delta": -37.3,
      "flag": "✓"
    }
  ],
  "by_league": [
    {
      "league": "Ligue 2",
      "total": 5,
      "errors": 4,
      "error_rate": 80.0,
      "delta": 42.7,
      "flag": "⚠️"
    },
    {
      "league": "League of Ireland Premier Division",
      "total": 3,
      "errors": 2,
      "error_rate": 66.7,
      "delta": 29.4,
      "flag": "⚠️"
    },
    {
      "league": "2. Bundesliga",
      "total": 6,
      "errors": 3,
      "error_rate": 50.0,
      "delta": 12.7,
      "flag": "⚠️"
    },
    {
      "league": "Premier League",
      "total": 10,
      "errors": 5,
      "error_rate": 50.0,
      "delta": 12.7,
      "flag": "⚠️"
    },
    {
      "league": "Scottish Premiership",
      "total": 2,
      "errors": 1,
      "error_rate": 50.0,
      "delta": 12.7,
      "flag": "⚠️"
    },
    {
      "league": "Serie A",
      "total": 8,
      "errors": 4,
      "error_rate": 50.0,
      "delta": 12.7,
      "flag": "⚠️"
    },
    {
      "league": "Süper Lig",
      "total": 6,
      "errors": 3,
      "error_rate": 50.0,
      "delta": 12.7,
      "flag": "⚠️"
    },
    {
      "league": "Serie C - Girone B",
      "total": 15,
      "errors": 7,
      "error_rate": 46.7,
      "delta": 9.4,
      "flag": "⚠️"
    },
    {
      "league": "Primera División",
      "total": 7,
      "errors": 3,
      "error_rate": 42.9,
      "delta": 5.6,
      "flag": "⚠️"
    },
    {
      "league": "Serie C - Girone C",
      "total": 17,
      "errors": 7,
      "error_rate": 41.2,
      "delta": 3.9,
      "flag": ""
    },
    {
      "league": "La Liga",
      "total": 5,
      "errors": 2,
      "error_rate": 40.0,
      "delta": 2.7,
      "flag": ""
    },
    {
      "league": "Championship",
      "total": 11,
      "errors": 4,
      "error_rate": 36.4,
      "delta": -0.9,
      "flag": ""
    },
    {
      "league": "Ligue 1",
      "total": 6,
      "errors": 2,
      "error_rate": 33.3,
      "delta": -4.0,
      "flag": "✓"
    },
    {
      "league": "Major League Soccer",
      "total": 12,
      "errors": 4,
      "error_rate": 33.3,
      "delta": -4.0,
      "flag": "✓"
    },
    {
      "league": "Serie C - Girone A",
      "total": 13,
      "errors": 4,
      "error_rate": 30.8,
      "delta": -6.5,
      "flag": "✓"
    },
    {
      "league": "Eredivisie",
      "total": 10,
      "errors": 3,
      "error_rate": 30.0,
      "delta": -7.3,
      "flag": "✓"
    },
    {
      "league": "Serie B",
      "total": 15,
      "errors": 4,
      "error_rate": 26.7,
      "delta": -10.6,
      "flag": "✓"
    },
    {
      "league": "Jupiler Pro League",
      "total": 5,
      "errors": 1,
      "error_rate": 20.0,
      "delta": -17.3,
      "flag": "✓"
    },
    {
      "league": "Bundesliga",
      "total": 6,
      "errors": 0,
      "error_rate": 0.0,
      "delta": -37.3,
      "flag": "✓"
    },
    {
      "league": "LaLiga 2",
      "total": 4,
      "errors": 0,
      "error_rate": 0.0,
      "delta": -37.3,
      "flag": "✓"
    },
    {
      "league": "Liga Portugal",
      "total": 3,
      "errors": 0,
      "error_rate": 0.0,
      "delta": -37.3,
      "flag": "✓"
    }
  ],
  "alto_rendimento_detail": {
    "by_quota_range": [
      {
        "range": "3.10-3.50",
        "total": 4,
        "errors": 3,
        "error_rate": 75.0,
        "profit_loss": -2.5
      },
      {
        "range": ">3.50",
        "total": 6,
        "errors": 5,
        "error_rate": 83.3,
        "profit_loss": -4.0
      }
    ],
    "total_pl": -6.5
  },
  "cross_analysis": {
    "source_x_league": [
      {
        "source": "C_screm",
        "league": "Serie C - Girone B",
        "total": 6,
        "errors": 4,
        "error_rate": 66.7,
        "delta": 29.4,
        "flag": "🔴"
      },
      {
        "source": "C_screm",
        "league": "Serie C - Girone C",
        "total": 6,
        "errors": 4,
        "error_rate": 66.7,
        "delta": 29.4,
        "flag": "🔴"
      },
      {
        "source": "C",
        "league": "Championship",
        "total": 5,
        "errors": 3,
        "error_rate": 60.0,
        "delta": 22.7,
        "flag": "🔴"
      },
      {
        "source": "C",
        "league": "Premier League",
        "total": 5,
        "errors": 3,
        "error_rate": 60.0,
        "delta": 22.7,
        "flag": "🔴"
      },
      {
        "source": "C",
        "league": "Serie C - Girone A",
        "total": 7,
        "errors": 4,
        "error_rate": 57.1,
        "delta": 19.8,
        "flag": "🔴"
      },
      {
        "source": "C_screm",
        "league": "Serie B",
        "total": 7,
        "errors": 2,
        "error_rate": 28.6,
        "delta": -8.7,
        "flag": "🟢"
      },
      {
        "source": "C",
        "league": "Serie C - Girone C",
        "total": 5,
        "errors": 1,
        "error_rate": 20.0,
        "delta": -17.3,
        "flag": "🟢"
      },
      {
        "source": "A+S",
        "league": "Eredivisie",
        "total": 5,
        "errors": 1,
        "error_rate": 20.0,
        "delta": -17.3,
        "flag": "🟢"
      },
      {
        "source": "C",
        "league": "Serie B",
        "total": 5,
        "errors": 0,
        "error_rate": 0.0,
        "delta": -37.3,
        "flag": "🟢"
      }
    ],
    "by_quota_range": [
      {
        "range": "1.35-1.55",
        "total": 54,
        "errors": 14,
        "error_rate": 25.9
      },
      {
        "range": "1.55-1.75",
        "total": 71,
        "errors": 28,
        "error_rate": 39.4
      },
      {
        "range": "1.75-1.95",
        "total": 22,
        "errors": 10,
        "error_rate": 45.5
      },
      {
        "range": "1.95-2.15",
        "total": 17,
        "errors": 9,
        "error_rate": 52.9
      },
      {
        "range": "2.15-2.35",
        "total": 4,
        "errors": 2,
        "error_rate": 50.0
      },
      {
        "range": "2.35-2.50",
        "total": 1,
        "errors": 0,
        "error_rate": 0.0
      }
    ],
    "quota_x_source": [
      {
        "range": "1.95-2.15",
        "source": "C",
        "total": 14,
        "errors": 8,
        "error_rate": 57.1,
        "delta": 19.8,
        "flag": "🔴"
      },
      {
        "range": "1.55-1.75",
        "source": "A",
        "total": 6,
        "errors": 3,
        "error_rate": 50.0,
        "delta": 12.7,
        "flag": "🟡"
      },
      {
        "range": "1.55-1.75",
        "source": "C_screm",
        "total": 15,
        "errors": 7,
        "error_rate": 46.7,
        "delta": 9.4,
        "flag": "🟡"
      },
      {
        "range": "1.35-1.55",
        "source": "C_screm",
        "total": 22,
        "errors": 6,
        "error_rate": 27.3,
        "delta": -10.0,
        "flag": "✓"
      },
      {
        "range": "1.35-1.55",
        "source": "A+S",
        "total": 13,
        "errors": 3,
        "error_rate": 23.1,
        "delta": -14.2,
        "flag": "✓"
      },
      {
        "range": "1.55-1.75",
        "source": "C_mg",
        "total": 5,
        "errors": 1,
        "error_rate": 20.0,
        "delta": -17.3,
        "flag": "✓"
      }
    ]
  },
  "weekly_trend": [
    {
      "week": "2026-W10",
      "total": 165,
      "errors": 64,
      "error_rate": 38.8,
      "delta_prev": null,
      "trend": "—",
      "small_sample": false
    },
    {
      "week": "2026-W11",
      "total": 14,
      "errors": 7,
      "error_rate": 50.0,
      "delta_prev": 11.2,
      "trend": "—",
      "small_sample": true
    }
  ],
  "weekly_warning": null,
  "patterns_detected": [
    {
      "name": "Source C con quota 1.95-2.15",
      "positive": false,
      "color": "🔴",
      "where": "Source C × fascia quota 1.95-2.15",
      "total": 14,
      "errors": 8,
      "error_rate": 57.1,
      "delta": 19.8,
      "impact_pl": -7.9
    },
    {
      "name": "Source C_screm con quota 1.55-1.75",
      "positive": false,
      "color": "🟡",
      "where": "Source C_screm × fascia quota 1.55-1.75",
      "total": 15,
      "errors": 7,
      "error_rate": 46.7,
      "delta": 9.4,
      "impact_pl": -2.07
    }
  ],
  "recommendations": [
    "MONITORARE: Source C con quota 1.95-2.15 — tasso errore 57.1% (+19.8% vs media 37.3%). Campione piccolo (14) ma anomalia forte. Se persiste a 20+ pronostici, ridurre stake del 50%.",
    "RIDURRE STAKE: Source C_screm con quota 1.55-1.75 — tasso errore 46.7% (+9.4% vs media 37.3%). Ridurre stake del 30% e cap confidence a 55%. P/L: -2.07"
  ]
}